overrides/conf.py
overrides/version.py
overrides/states/recursive_contracts/recreate.py
pop_overrides-0.0.0.post1.dist-info/LICENSE
pop_overrides-0.0.0.post1.dist-info/METADATA
pop_overrides-0.0.0.post1.dist-info/WHEEL
pop_overrides-0.0.0.post1.dist-info/top_level.txt
pop_overrides-0.0.0.post1.dist-info/RECORD
